selenium_youtube_firefox/__init__.py
selenium_youtube_firefox/youtube.py
selenium_youtube_firefox-0.0.2.dist-info/LICENSE
selenium_youtube_firefox-0.0.2.dist-info/METADATA
selenium_youtube_firefox-0.0.2.dist-info/WHEEL
selenium_youtube_firefox-0.0.2.dist-info/top_level.txt
selenium_youtube_firefox-0.0.2.dist-info/RECORD
