Metadata-Version: 2.1
Name: selenium-youtube-firefox
Version: 0.0.2
Summary: selenium_youtube_firefox
Home-page: https://github.com/kkristof200/selenium_youtube_firefox
Author: Kristóf-Attila Kovács
License: UNKNOWN
Platform: UNKNOWN
Classifier: Programming Language :: Python :: 3.4
Classifier: Programming Language :: Python :: 3.5
Classifier: Programming Language :: Python :: 3.6
Classifier: Programming Language :: Python :: 3.7
Classifier: Programming Language :: Python :: 3.8
Classifier: Programming Language :: Python :: 3.9
Classifier: License :: OSI Approved :: MIT License
Classifier: Operating System :: OS Independent
Requires-Python: >=3.4
License-File: LICENSE
Requires-Dist: kproxy (>=0.0.2)
Requires-Dist: selenium-firefox (>=2.0.7)
Requires-Dist: selenium-youtube (>=2.0.3)
